LICENSE
MANIFEST.in
README.rst
requirements-test-py26.txt
requirements-test.txt
setup.py
recursely/__init__.py
recursely/_compat.py
recursely/hook.py
recursely/importer.py
recursely/utils.py
recursely.egg-info/PKG-INFO
recursely.egg-info/SOURCES.txt
recursely.egg-info/dependency_links.txt
recursely.egg-info/top_level.txt