Metadata-Version: 1.1
Name: recursely
Version: 0.0.3
Summary: Recursive importer for Python submodules
Home-page: http://github.com/Xion/recursely
Author: Karol Kuczmarski
Author-email: karol.kuczmarski@gmail.com
License: Simplified BSD
Platform: any
Classifier: Development Status :: 1 - Planning
Classifier: Intended Audience :: Developers
Classifier: License :: OSI Approved :: BSD License
Classifier: Operating System :: OS Independent
Classifier: Programming Language :: Python
Classifier: Programming Language :: Python :: 2.6
Classifier: Programming Language :: Python :: 2.7
Classifier: Programming Language :: Python :: 3.3
Classifier: Programming Language :: Python :: Implementation :: PyPy
